China_coord_utils.py
LICENSE
MANIFEST.in
setup.cfg
setup.py
China_coord_utils.egg-info/PKG-INFO
China_coord_utils.egg-info/SOURCES.txt
China_coord_utils.egg-info/dependency_links.txt
China_coord_utils.egg-info/not-zip-safe
China_coord_utils.egg-info/requires.txt
China_coord_utils.egg-info/top_level.txt